HellozookeeperFix1/README.md
HellozookeeperFix1/__init__.py
HellozookeeperFix1/__main__.py
HellozookeeperFix1/file.epub
HellozookeeperFix1/index.html
HellozookeeperFix1/css/__init__.py
HellozookeeperFix1/css/annotations.css
HellozookeeperFix1/css/main.css
HellozookeeperFix1/css/normalize.css
HellozookeeperFix1/css/popup.css
HellozookeeperFix1/font/__init__.py
HellozookeeperFix1/font/fontello.eot
HellozookeeperFix1/font/fontello.svg
HellozookeeperFix1/font/fontello.ttf
HellozookeeperFix1/font/fontello.woff
HellozookeeperFix1/img/__init__.py
HellozookeeperFix1/img/annotator-glyph-sprite.png
HellozookeeperFix1/img/annotator-icon-sprite.png
HellozookeeperFix1/img/apple-touch-icon.png
HellozookeeperFix1/img/cancelfullscreen.png
HellozookeeperFix1/img/close.png
HellozookeeperFix1/img/fullscreen.png
HellozookeeperFix1/img/loader.gif
HellozookeeperFix1/img/menu-icon.png
HellozookeeperFix1/img/save.png
HellozookeeperFix1/img/saved.png
HellozookeeperFix1/img/settings-s.png
HellozookeeperFix1/img/settings.png
HellozookeeperFix1/img/star.png
HellozookeeperFix1/js/__init__.py
HellozookeeperFix1/js/epub.js
HellozookeeperFix1/js/epub.min.js
HellozookeeperFix1/js/epub.min.map
HellozookeeperFix1/js/hooks.min.js
HellozookeeperFix1/js/hooks.min.map
HellozookeeperFix1/js/reader.js
HellozookeeperFix1/js/reader.js.map
HellozookeeperFix1/js/reader.min.js
HellozookeeperFix1/js/reader.min.map
HellozookeeperFix1/js/hooks/__init__.py
HellozookeeperFix1/js/hooks/extensions/__init__.py
HellozookeeperFix1/js/hooks/extensions/highlight.js
HellozookeeperFix1/js/libs/__init__.py
HellozookeeperFix1/js/libs/jquery.min.js
HellozookeeperFix1/js/libs/localforage.min.js
HellozookeeperFix1/js/libs/screenfull.js
HellozookeeperFix1/js/libs/screenfull.min.js
HellozookeeperFix1/js/libs/zip.min.js
HellozookeeperFix1/js/plugins/__init__.py
HellozookeeperFix1/js/plugins/hypothesis.js
HellozookeeperFix1/js/plugins/search.js
hellozookeeper_fix1-2025.3.25.1.dist-info/METADATA
hellozookeeper_fix1-2025.3.25.1.dist-info/WHEEL
hellozookeeper_fix1-2025.3.25.1.dist-info/entry_points.txt
hellozookeeper_fix1-2025.3.25.1.dist-info/top_level.txt
hellozookeeper_fix1-2025.3.25.1.dist-info/RECORD
